embedding4bert/__init__.py
embedding4bert/embedding4bert.py
embedding4bert/embeddings4bert.py
embedding4bert/test_xlnet_embedding.py
embedding4bert-0.0.4.dist-info/METADATA
embedding4bert-0.0.4.dist-info/WHEEL
embedding4bert-0.0.4.dist-info/top_level.txt
embedding4bert-0.0.4.dist-info/RECORD
