Metadata-Version: 2.1
Name: embedding4bert
Version: 0.0.4
Summary: A package for extracting word representations from BERT/XLNet
Home-page: https://github.com/cyk1337/embedding4bert
Author: cyk1337
Author-email: chaiyekun@gmail.com
License: UNKNOWN
Platform: UNKNOWN
Classifier: Programming Language :: Python :: 3
Classifier: License :: OSI Approved :: MIT License
Classifier: Operating System :: OS Independent
Requires-Dist: transformers
Requires-Dist: torch
Requires-Dist: sentencepiece
